<?xml version="1.0" encoding="utf-8" standalone="yes"?>
<!DOCTYPE ROOT PUBLIC "" ""[]>
<PresetModel xmlns:r="reflection" r:Version="2">
  <ChannelValues>
    <Item Key="Config.Attraction matrix">
      <Value r:Type="AttractionMatrix [Main]">
        <Attraction_matrix>
          <Item>-1, 0.0057142973, -0.26, 0.038571447, 0.074285686</Item>
          <Item>-0.33428568, -1, -0.28285712, -0.2, -1</Item>
          <Item>-0.28, -0.024285704, -1, -0.44, -0.112857185</Item>
          <Item>-0.21, -0.1, -0.13, -1, -0.45</Item>
          <Item>-0.3299999, -0.37, -0.33142856, -0.77, -1</Item>
        </Attraction_matrix>
      </Value>
    </Item>
    <Item Key="Config.Force factor">
      <Value r:Type="Float32 [Primitive]">1.2</Value>
    </Item>
    <Item Key="Config.Friction">
      <Value r:Type="Float32 [Primitive]">0.07</Value>
    </Item>
    <Item Key="Config.Interaction radius">
      <Value r:Type="Float32 [Primitive]">0.42</Value>
    </Item>
    <Item Key="Config.Minimum distance">
      <Value r:Type="Float32 [Primitive]">0.06</Value>
    </Item>
    <Item Key="Config.Particle count">
      <Value r:Type="Integer32 [Primitive]">250</Value>
    </Item>
    <Item Key="Config.Time step">
      <Value r:Type="Float32 [Primitive]">0.005</Value>
    </Item>
  </ChannelValues>
</PresetModel>