<?xml version="1.0" encoding="UTF-8"?>
<current>
	<city id="2950159" name="Berlin">
		<coord lon="13.39" lat="52.52"/>
		<country>DE</country>
		<sun rise="2019-01-25T06:58:23" set="2019-01-25T15:39:47"/>
	</city>
	<temperature value="-3.49" min="-4" max="-3" unit="metric"/>
	<humidity value="73" unit="%"/>
	<pressure value="1015" unit="hPa"/>
	<wind>
		<speed value="2.6" name="Light breeze"/>
		<gusts/>
		<direction value="280" code="W" name="West"/>
	</wind>
	<clouds value="75" name="broken clouds"/>
	<visibility value="10000"/>
	<precipitation mode="no"/>
	<weather number="803" value="broken clouds" icon="04d"/>
	<lastupdate value="2019-01-25T10:50:00"/>
</current>